dashboards_app/__init__.py
dashboards_app/admin.py
dashboards_app/apps.py
dashboards_app/cms_appconfig.py
dashboards_app/cms_apps.py
dashboards_app/cms_menus.py
dashboards_app/cms_plugins.py
dashboards_app/cms_toolbars.py
dashboards_app/cms_wizards.py
dashboards_app/feeds.py
dashboards_app/forms.py
dashboards_app/managers.py
dashboards_app/models.py
dashboards_app/search_indexes.py
dashboards_app/urls.py
dashboards_app/views.py
dashboards_app/blero_utils/FormFunctionUtils.py
dashboards_app/blero_utils/__init__.py
dashboards_app/blero_utils/utils.py
dashboards_app/blero_utils/client_utils/__init__.py
dashboards_app/blero_utils/client_utils/client_to_server.py
dashboards_app/blero_utils/client_utils/logging_helpers.py
dashboards_app/blero_utils/client_utils/settings.py
dashboards_app/boilerplates/bootstrap3/private/img/future.psd
dashboards_app/boilerplates/bootstrap3/private/img/unpublished.psd
dashboards_app/boilerplates/bootstrap3/static/css/aldryn-newsblog/article.css
dashboards_app/boilerplates/bootstrap3/static/img/aldryn_newsblog/future.png
dashboards_app/boilerplates/bootstrap3/static/img/aldryn_newsblog/no-photo.png
dashboards_app/boilerplates/bootstrap3/static/img/aldryn_newsblog/unpublished.png
dashboards_app/boilerplates/bootstrap3/static/js/addons/cl.newsblog.js
dashboards_app/boilerplates/bootstrap3/static/js/libs/jquery.min.js
dashboards_app/boilerplates/bootstrap3/templates/aldryn_newsblog/article_detail.html
dashboards_app/boilerplates/bootstrap3/templates/aldryn_newsblog/article_list.html
dashboards_app/boilerplates/bootstrap3/templates/aldryn_newsblog/base.html
dashboards_app/boilerplates/bootstrap3/templates/aldryn_newsblog/fullwidth.html
dashboards_app/boilerplates/bootstrap3/templates/aldryn_newsblog/two_column.html
dashboards_app/boilerplates/bootstrap3/templates/aldryn_newsblog/includes/article.html
dashboards_app/boilerplates/bootstrap3/templates/aldryn_newsblog/includes/author.html
dashboards_app_blero-1.1.dist-info/LICENSE
dashboards_app_blero-1.1.dist-info/METADATA
dashboards_app_blero-1.1.dist-info/WHEEL
dashboards_app_blero-1.1.dist-info/top_level.txt
dashboards_app_blero-1.1.dist-info/RECORD
